cdk_nag/__init__.py
cdk_nag/py.typed
cdk_nag/_jsii/__init__.py
cdk_nag/_jsii/cdk-nag@2.37.55.jsii.tgz
cdk_nag-2.37.55.dist-info/LICENSE
cdk_nag-2.37.55.dist-info/METADATA
cdk_nag-2.37.55.dist-info/NOTICE
cdk_nag-2.37.55.dist-info/WHEEL
cdk_nag-2.37.55.dist-info/top_level.txt
cdk_nag-2.37.55.dist-info/RECORD
