Metadata-Version: 2.1
Name: cdk-nag
Version: 2.37.55
Summary: Check CDK v2 applications for best practices using a combination on available rule packs.
Home-page: https://github.com/cdklabs/cdk-nag.git
Author: Arun Donti<donti@amazon.com>
License: Apache-2.0
Project-URL: Source, https://github.com/cdklabs/cdk-nag.git
Classifier: Intended Audience :: Developers
Classifier: Operating System :: OS Independent
Classifier: Programming Language :: JavaScript
Classifier: Programming Language :: Python :: 3 :: Only
Classifier: Programming Language :: Python :: 3.9
Classifier: Programming Language :: Python :: 3.10
Classifier: Programming Language :: Python :: 3.11
Classifier: Typing :: Typed
Classifier: Development Status :: 5 - Production/Stable
Classifier: License :: OSI Approved
Requires-Python: ~=3.9
License-File: LICENSE
License-File: NOTICE
Requires-Dist: aws-cdk-lib<3.0.0,>=2.176.0
Requires-Dist: constructs<11.0.0,>=10.0.5
Requires-Dist: jsii<2.0.0,>=1.116.0
Requires-Dist: publication>=0.0.3
Requires-Dist: typeguard<4.3.0,>=2.13.3
